{
  "schema_version": 1,
  "quilt_loader": {
    "group": "org.quiltmc.qsl.core",
    "id": "quilt_registry_testmod",
    "version": "1.0.0",
    "metadata": {
      "name": "Quilt Registry Library Test Mod",
      "license": "Apache-2.0"
    },
    "intermediate_mappings": "net.fabricmc:intermediary",
    "load_type": "always",
    "entrypoints": {
      "init": [
        "org.quiltmc.qsl.registry.test.RegistryLibEventsTest",
        "org.quiltmc.qsl.registry.test.RegistryLibMonitorRegistrationTest",
        "org.quiltmc.qsl.registry.test.RegistryLibMonitorTest",
        "org.quiltmc.qsl.registry.test.RegistryLibSyncTest"
      ]
    },
    "depends": [
      "quilt_loader",
      "quilt_registry"
    ]
  }
}
